ver17/__init__.py
ver17/images/__init__.py
ver17/images/about1.png
ver17/images/cs.png
ver17/images/doc.png
ver17/images/folder_icon.png
ver17/images/initial1.png
ver17/images/java1.png
ver17/images/logo.png
ver17/images/py.png
ver17/modules/AIUT_Core_CSharp.py
ver17/modules/AIUT_Core_Java.py
ver17/modules/AIUT_Core_Python.py
ver17/modules/AIUT_Helper.py
ver17/modules/__init__.py
ver17/modules/sub.py
ver17/requirements/__init__.py
ver17/requirements/requirements.txt
ver17/settings/UT_Settings.ini
ver17/settings/__init__.py
ver17/src/AIUT.py
ver17/src/__init__.py
ver17-0.1.dist-info/METADATA
ver17-0.1.dist-info/WHEEL
ver17-0.1.dist-info/entry_points.txt
ver17-0.1.dist-info/license.txt
ver17-0.1.dist-info/top_level.txt
ver17-0.1.dist-info/RECORD
